{
  "fetched_at": "2026-06-05T18:30:09.641973+00:00",
  "gbp_usd_rate": 1.334,
  "portfolio": [
    {
      "ticker": "NVDA",
      "yahoo_symbol": "NVDA",
      "name": "NVIDIA Corporation",
      "shares": 100,
      "avg_cost_usd": 218.66,
      "price_usd": 205.98,
      "change_usd": -5.16,
      "change_pct": -2.4439,
      "prev_close_raw": 211.14,
      "currency": "USD",
      "gbp_usd_rate": null
    },
    {
      "ticker": "AAPL",
      "yahoo_symbol": "AAPL",
      "name": "Apple Inc",
      "shares": 100,
      "avg_cost_usd": 311.23,
      "price_usd": 311.54,
      "change_usd": -0.52,
      "change_pct": -0.1666,
      "prev_close_raw": 312.06,
      "currency": "USD",
      "gbp_usd_rate": null
    },
    {
      "ticker": "AMD",
      "yahoo_symbol": "AMD",
      "name": "Advanced Micro Devices",
      "shares": 100,
      "avg_cost_usd": 523.2,
      "price_usd": 469.54,
      "change_usd": -46.56,
      "change_pct": -9.0215,
      "prev_close_raw": 516.1,
      "currency": "USD",
      "gbp_usd_rate": null
    },
    {
      "ticker": "TSLA",
      "yahoo_symbol": "TSLA",
      "name": "Tesla Inc",
      "shares": 100,
      "avg_cost_usd": 418.45,
      "price_usd": 391.64,
      "change_usd": -44.15,
      "change_pct": -10.131,
      "prev_close_raw": 435.79,
      "currency": "USD",
      "gbp_usd_rate": null
    },
    {
      "ticker": "AMZN",
      "yahoo_symbol": "AMZN",
      "name": "Amazon.com Inc",
      "shares": 100,
      "avg_cost_usd": 253.79,
      "price_usd": 248.855,
      "change_usd": -21.785,
      "change_pct": -8.0494,
      "prev_close_raw": 270.64,
      "currency": "USD",
      "gbp_usd_rate": null
    },
    {
      "ticker": "META",
      "yahoo_symbol": "META",
      "name": "Meta Platforms Inc",
      "shares": 100,
      "avg_cost_usd": 627.57,
      "price_usd": 586.7,
      "change_usd": -45.81,
      "change_pct": -7.2426,
      "prev_close_raw": 632.51,
      "currency": "USD",
      "gbp_usd_rate": null
    },
    {
      "ticker": "PLTR",
      "yahoo_symbol": "PLTR",
      "name": "Palantir Technologies",
      "shares": 100,
      "avg_cost_usd": 24.8,
      "price_usd": 135.35,
      "change_usd": -21.19,
      "change_pct": -13.5365,
      "prev_close_raw": 156.54,
      "currency": "USD",
      "gbp_usd_rate": null
    },
    {
      "ticker": "WISE",
      "yahoo_symbol": "WISE.L",
      "name": "Wise plc (LSE)",
      "shares": 100,
      "avg_cost_usd": 9.85,
      "price_usd": 11.0188,
      "change_usd": -1.4407,
      "change_pct": -11.5632,
      "prev_close_raw": 934.0,
      "currency": "GBP",
      "gbp_usd_rate": 1.334
    },
    {
      "ticker": "MOH",
      "yahoo_symbol": "MOH",
      "name": "Molina Healthcare Inc",
      "shares": 100,
      "avg_cost_usd": 299.4,
      "price_usd": 191.085,
      "change_usd": 17.485,
      "change_pct": 10.072,
      "prev_close_raw": 173.6,
      "currency": "USD",
      "gbp_usd_rate": null
    }
  ],
  "signal_prices": {
    "ISRG": {
      "price": 424.01,
      "change": -0.63,
      "change_pct": -0.1484,
      "prev_close": 424.64
    },
    "AMZN": {
      "price": 248.855,
      "change": -21.785,
      "change_pct": -8.0494,
      "prev_close": 270.64
    },
    "PANW": {
      "price": 273.25,
      "change": -8.44,
      "change_pct": -2.9962,
      "prev_close": 281.69
    },
    "PLTR": {
      "price": 135.35,
      "change": -21.19,
      "change_pct": -13.5365,
      "prev_close": 156.54
    },
    "META": {
      "price": 586.7,
      "change": -45.81,
      "change_pct": -7.2426,
      "prev_close": 632.51
    },
    "NFLX": {
      "price": 81.565,
      "change": -4.455,
      "change_pct": -5.179,
      "prev_close": 86.02
    },
    "NVDA": {
      "price": 205.98,
      "change": -5.16,
      "change_pct": -2.4439,
      "prev_close": 211.14
    },
    "NKE": {
      "price": 42.91,
      "change": -3.32,
      "change_pct": -7.1815,
      "prev_close": 46.23
    },
    "ADBE": {
      "price": 251.75,
      "change": -7.46,
      "change_pct": -2.878,
      "prev_close": 259.21
    },
    "CRM": {
      "price": 186.63,
      "change": -4.47,
      "change_pct": -2.3391,
      "prev_close": 191.1
    },
    "TSLA": {
      "price": 391.64,
      "change": -44.15,
      "change_pct": -10.131,
      "prev_close": 435.79
    },
    "AMD": {
      "price": 469.54,
      "change": -46.56,
      "change_pct": -9.0215,
      "prev_close": 516.1
    },
    "T": {
      "price": 22.975,
      "change": -1.825,
      "change_pct": -7.3589,
      "prev_close": 24.8
    },
    "CVS": {
      "price": 96.14,
      "change": 5.16,
      "change_pct": 5.6716,
      "prev_close": 90.98
    },
    "INTU": {
      "price": 296.9,
      "change": -34.63,
      "change_pct": -10.4455,
      "prev_close": 331.53
    },
    "INTC": {
      "price": 101.4,
      "change": -13.28,
      "change_pct": -11.58,
      "prev_close": 114.68
    },
    "PFE": {
      "price": 26.12,
      "change": -0.06,
      "change_pct": -0.2292,
      "prev_close": 26.18
    },
    "MOH": {
      "price": 191.085,
      "change": 17.485,
      "change_pct": 10.072,
      "prev_close": 173.6
    },
    "AMAT": {
      "price": 462.94,
      "change": 12.88,
      "change_pct": 2.8618,
      "prev_close": 450.06
    },
    "SNOW": {
      "price": 236.87,
      "change": -18.68,
      "change_pct": -7.3097,
      "prev_close": 255.55
    },
    "NOW": {
      "price": 112.69,
      "change": -11.68,
      "change_pct": -9.3913,
      "prev_close": 124.37
    },
    "GOOGL": {
      "price": 367.25,
      "change": -13.09,
      "change_pct": -3.4417,
      "prev_close": 380.34
    },
    "AVGO": {
      "price": 390.355,
      "change": -56.415,
      "change_pct": -12.6273,
      "prev_close": 446.77
    },
    "MSFT": {
      "price": 418.29,
      "change": -31.95,
      "change_pct": -7.0962,
      "prev_close": 450.24
    },
    "AAPL": {
      "price": 311.52,
      "change": -0.54,
      "change_pct": -0.173,
      "prev_close": 312.06
    },
    "BA": {
      "price": 215.09,
      "change": -16.06,
      "change_pct": -6.9479,
      "prev_close": 231.15
    },
    "DIS": {
      "price": 99.285,
      "change": -2.545,
      "change_pct": -2.4993,
      "prev_close": 101.83
    },
    "UBER": {
      "price": 70.51,
      "change": 0.11,
      "change_pct": 0.1562,
      "prev_close": 70.4
    }
  }
}